kabbes_icloud/Connection.py
kabbes_icloud/ICloudContact.py
kabbes_icloud/ICloudContacts.py
kabbes_icloud/__init__.py
kabbes_icloud/__main__.py
kabbes_icloud-0.1.0.dist-info/LICENSE
kabbes_icloud-0.1.0.dist-info/METADATA
kabbes_icloud-0.1.0.dist-info/WHEEL
kabbes_icloud-0.1.0.dist-info/top_level.txt
kabbes_icloud-0.1.0.dist-info/RECORD
